[
    {
        "score": 0.9988516569137573,
        "part": "nose",
        "position": {
            "x": 397.2161995309298,
            "y": 219.32101942196923
        }
    },
    {
        "score": 0.9980144500732422,
        "part": "leftEye",
        "position": {
            "x": 408.55602677142036,
            "y": 211.49567746522519
        }
    },
    {
        "score": 0.9975281357765198,
        "part": "rightEye",
        "position": {
            "x": 387.0588629050333,
            "y": 210.50906577050935
        }
    },
    {
        "score": 0.7712410092353821,
        "part": "leftEar",
        "position": {
            "x": 426.6390631003458,
            "y": 218.05495048459636
        }
    },
    {
        "score": 0.8101351261138916,
        "part": "rightEar",
        "position": {
            "x": 372.63239250808465,
            "y": 215.66375954022547
        }
    },
    {
        "score": 0.9905989766120911,
        "part": "leftShoulder",
        "position": {
            "x": 430.6747311451396,
            "y": 277.8020775664397
        }
    },
    {
        "score": 0.9236317276954651,
        "part": "rightShoulder",
        "position": {
            "x": 350.76090828317115,
            "y": 263.4293607656392
        }
    },
    {
        "score": 0.9272079467773438,
        "part": "leftElbow",
        "position": {
            "x": 423.9402715964396,
            "y": 356.4365711449588
        }
    },
    {
        "score": 0.9609140753746033,
        "part": "rightElbow",
        "position": {
            "x": 318.31856349257174,
            "y": 305.9437106753781
        }
    },
    {
        "score": 0.7742148041725159,
        "part": "leftWrist",
        "position": {
            "x": 371.2004113119157,
            "y": 384.1054548366436
        }
    },
    {
        "score": 0.671754002571106,
        "part": "rightWrist",
        "position": {
            "x": 303.95200435450823,
            "y": 369.16347039685706
        }
    },
    {
        "score": 0.9320845603942871,
        "part": "leftHip",
        "position": {
            "x": 425.24642594134224,
            "y": 399.18496499912374
        }
    },
    {
        "score": 0.99698406457901,
        "part": "rightHip",
        "position": {
            "x": 372.054630217005,
            "y": 396.700868468067
        }
    },
    {
        "score": 0.49516767263412476,
        "part": "leftKnee",
        "position": {
            "x": 412.3375584336578,
            "y": 502.8641293157681
        }
    },
    {
        "score": 0.1766660064458847,
        "part": "rightKnee",
        "position": {
            "x": 368.7044737768955,
            "y": 494.26745576977237
        }
    },
    {
        "score": 0.06723755598068237,
        "part": "leftAnkle",
        "position": {
            "x": 433.4062787665696,
            "y": 512.8504300018565
        }
    },
    {
        "score": 0.09709687530994415,
        "part": "rightAnkle",
        "position": {
            "x": 384.51370689517165,
            "y": 515.5220229596024
        }
    }
]