[
    {
        "score": 0.9988505840301514,
        "part": "nose",
        "position": {
            "x": 365.8177332643603,
            "y": 113.19109117341735
        }
    },
    {
        "score": 0.9983999133110046,
        "part": "leftEye",
        "position": {
            "x": 377.2832446489178,
            "y": 103.79706922903101
        }
    },
    {
        "score": 0.9964827299118042,
        "part": "rightEye",
        "position": {
            "x": 358.40133616963374,
            "y": 103.35373433299085
        }
    },
    {
        "score": 0.9141629338264465,
        "part": "leftEar",
        "position": {
            "x": 393.24293092821466,
            "y": 110.87960128467608
        }
    },
    {
        "score": 0.8241442441940308,
        "part": "rightEar",
        "position": {
            "x": 345.94287309490267,
            "y": 107.9800752188655
        }
    },
    {
        "score": 0.9979110956192017,
        "part": "leftShoulder",
        "position": {
            "x": 408.2285451420018,
            "y": 166.76390727525927
        }
    },
    {
        "score": 0.9982278943061829,
        "part": "rightShoulder",
        "position": {
            "x": 324.58941350217725,
            "y": 153.73102955798393
        }
    },
    {
        "score": 0.8665235042572021,
        "part": "leftElbow",
        "position": {
            "x": 401.44578877433406,
            "y": 247.58518583052387
        }
    },
    {
        "score": 0.9915825724601746,
        "part": "rightElbow",
        "position": {
            "x": 266.2884286348937,
            "y": 199.10019055719943
        }
    },
    {
        "score": 0.6213288903236389,
        "part": "leftWrist",
        "position": {
            "x": 342.63532995005124,
            "y": 293.85924586616613
        }
    },
    {
        "score": 0.7857338190078735,
        "part": "rightWrist",
        "position": {
            "x": 202.08331999231558,
            "y": 256.67243181917183
        }
    },
    {
        "score": 0.9904921650886536,
        "part": "leftHip",
        "position": {
            "x": 397.7186759573515,
            "y": 308.30729255043127
        }
    },
    {
        "score": 0.8091480135917664,
        "part": "rightHip",
        "position": {
            "x": 339.98638015496925,
            "y": 310.06364901530793
        }
    },
    {
        "score": 0.03510269522666931,
        "part": "leftKnee",
        "position": {
            "x": 356.9005427126025,
            "y": 375.83349849178586
        }
    },
    {
        "score": 0.5279395580291748,
        "part": "rightKnee",
        "position": {
            "x": 328.4241323002049,
            "y": 411.2793736438039
        }
    },
    {
        "score": 0.10114947706460953,
        "part": "leftAnkle",
        "position": {
            "x": 336.293993340164,
            "y": 443.8352614517529
        }
    },
    {
        "score": 0.42317327857017517,
        "part": "rightAnkle",
        "position": {
            "x": 323.70554239241807,
            "y": 460.43022440676873
        }
    }
]