[
    {
        "score": 0.9947210550308228,
        "part": "nose",
        "position": {
            "x": 313.5874453685323,
            "y": 184.31329034670756
        }
    },
    {
        "score": 0.9949978590011597,
        "part": "leftEye",
        "position": {
            "x": 320.7393198482326,
            "y": 176.66905252765324
        }
    },
    {
        "score": 0.9924612641334534,
        "part": "rightEye",
        "position": {
            "x": 306.7236753369941,
            "y": 177.5176436079983
        }
    },
    {
        "score": 0.4565686583518982,
        "part": "leftEar",
        "position": {
            "x": 328.4493708376025,
            "y": 179.29888365179673
        }
    },
    {
        "score": 0.9065632820129395,
        "part": "rightEar",
        "position": {
            "x": 285.27461217661374,
            "y": 180.42985433364805
        }
    },
    {
        "score": 0.7856680154800415,
        "part": "leftShoulder",
        "position": {
            "x": 345.4593565893955,
            "y": 227.90443847782882
        }
    },
    {
        "score": 0.7768433690071106,
        "part": "rightShoulder",
        "position": {
            "x": 268.1832335425205,
            "y": 225.902613267859
        }
    },
    {
        "score": 0.9688367247581482,
        "part": "leftElbow",
        "position": {
            "x": 408.2740243380187,
            "y": 202.5684526352467
        }
    },
    {
        "score": 0.5874964594841003,
        "part": "rightElbow",
        "position": {
            "x": 200.79725121670083,
            "y": 187.9160948314113
        }
    },
    {
        "score": 0.7094197273254395,
        "part": "leftWrist",
        "position": {
            "x": 365.1346375512295,
            "y": 161.25204751105724
        }
    },
    {
        "score": 0.17879319190979004,
        "part": "rightWrist",
        "position": {
            "x": 259.5407034451844,
            "y": 165.3979942511721
        }
    },
    {
        "score": 0.9976611137390137,
        "part": "leftHip",
        "position": {
            "x": 341.03063764728483,
            "y": 368.26837606944486
        }
    },
    {
        "score": 0.9467031955718994,
        "part": "rightHip",
        "position": {
            "x": 293.00375616355024,
            "y": 372.6593290621809
        }
    },
    {
        "score": 0.9458650946617126,
        "part": "leftKnee",
        "position": {
            "x": 357.5687996285861,
            "y": 470.1114967156248
        }
    },
    {
        "score": 0.853969395160675,
        "part": "rightKnee",
        "position": {
            "x": 298.3489429911629,
            "y": 460.7188778299514
        }
    },
    {
        "score": 0.5017186403274536,
        "part": "leftAnkle",
        "position": {
            "x": 355.3359114850154,
            "y": 505.6636318626246
        }
    },
    {
        "score": 0.18343135714530945,
        "part": "rightAnkle",
        "position": {
            "x": 309.13864786116807,
            "y": 490.9849468603174
        }
    }
]