[
    {
        "score": 0.9860761165618896,
        "part": "nose",
        "position": {
            "x": 247.58335000960554,
            "y": 123.20250693198557
        }
    },
    {
        "score": 0.9386044144630432,
        "part": "leftEye",
        "position": {
            "x": 258.67871293865267,
            "y": 113.83319197848625
        }
    },
    {
        "score": 0.9696211814880371,
        "part": "rightEye",
        "position": {
            "x": 242.850965656218,
            "y": 119.92594315303313
        }
    },
    {
        "score": 0.555432140827179,
        "part": "leftEar",
        "position": {
            "x": 259.39513059522284,
            "y": 119.52681660157518
        }
    },
    {
        "score": 0.9044391512870789,
        "part": "rightEar",
        "position": {
            "x": 232.3770339215388,
            "y": 126.96437073941054
        }
    },
    {
        "score": 0.9917550086975098,
        "part": "leftShoulder",
        "position": {
            "x": 287.51824050653175,
            "y": 145.0963811755675
        }
    },
    {
        "score": 0.5446367263793945,
        "part": "rightShoulder",
        "position": {
            "x": 222.34809250128075,
            "y": 159.6409641360841
        }
    },
    {
        "score": 0.40399032831192017,
        "part": "leftElbow",
        "position": {
            "x": 299.6997905793737,
            "y": 101.22498041366642
        }
    },
    {
        "score": 0.45750612020492554,
        "part": "rightElbow",
        "position": {
            "x": 195.8026213098745,
            "y": 97.93049270186683
        }
    },
    {
        "score": 0.509208619594574,
        "part": "leftWrist",
        "position": {
            "x": 295.8729728323514,
            "y": 40.220329870326886
        }
    },
    {
        "score": 0.4949241578578949,
        "part": "rightWrist",
        "position": {
            "x": 177.14898381467725,
            "y": 52.788092387662395
        }
    },
    {
        "score": 0.9953145980834961,
        "part": "leftHip",
        "position": {
            "x": 293.48380867379615,
            "y": 279.25975886617954
        }
    },
    {
        "score": 0.9852853417396545,
        "part": "rightHip",
        "position": {
            "x": 260.88437540023057,
            "y": 283.5117237201865
        }
    },
    {
        "score": 0.9925848841667175,
        "part": "leftKnee",
        "position": {
            "x": 305.3822524273982,
            "y": 366.45450767639767
        }
    },
    {
        "score": 0.976134181022644,
        "part": "rightKnee",
        "position": {
            "x": 257.4874667808658,
            "y": 367.10459364895013
        }
    },
    {
        "score": 0.8328748345375061,
        "part": "leftAnkle",
        "position": {
            "x": 305.30552598296623,
            "y": 446.5986594124949
        }
    },
    {
        "score": 0.6786295175552368,
        "part": "rightAnkle",
        "position": {
            "x": 273.6649830302254,
            "y": 448.28716650048733
        }
    }
]