[
    {
        "score": 0.9977533221244812,
        "part": "nose",
        "position": {
            "x": 537.0579680771125,
            "y": 179.76600005913573
        }
    },
    {
        "score": 0.9969815015792847,
        "part": "leftEye",
        "position": {
            "x": 544.7206595999296,
            "y": 175.86940848481112
        }
    },
    {
        "score": 0.9934792518615723,
        "part": "rightEye",
        "position": {
            "x": 520.0706446913423,
            "y": 175.85289923481923
        }
    },
    {
        "score": 0.7894383072853088,
        "part": "leftEar",
        "position": {
            "x": 553.265649013832,
            "y": 177.83062487716992
        }
    },
    {
        "score": 0.922140896320343,
        "part": "rightEar",
        "position": {
            "x": 510.97220899237965,
            "y": 179.7843335575088
        }
    },
    {
        "score": 0.8902803659439087,
        "part": "leftShoulder",
        "position": {
            "x": 566.8574401355181,
            "y": 230.00475776640707
        }
    },
    {
        "score": 0.49804869294166565,
        "part": "rightShoulder",
        "position": {
            "x": 502.8368580302254,
            "y": 232.759928802237
        }
    },
    {
        "score": 0.09608684480190277,
        "part": "leftElbow",
        "position": {
            "x": 602.250256147541,
            "y": 199.91679804948356
        }
    },
    {
        "score": 0.5203333497047424,
        "part": "rightElbow",
        "position": {
            "x": 466.3673583484087,
            "y": 184.94587419438662
        }
    },
    {
        "score": 0.08133979886770248,
        "part": "leftWrist",
        "position": {
            "x": 613.0069480020492,
            "y": 102.99060948162159
        }
    },
    {
        "score": 0.6723611354827881,
        "part": "rightWrist",
        "position": {
            "x": 471.1841011672724,
            "y": 98.3834484306114
        }
    },
    {
        "score": 0.9751002788543701,
        "part": "leftHip",
        "position": {
            "x": 552.728843814037,
            "y": 374.61525770638497
        }
    },
    {
        "score": 0.35061579942703247,
        "part": "rightHip",
        "position": {
            "x": 499.1052956502946,
            "y": 390.16385296073696
        }
    },
    {
        "score": 0.829055905342102,
        "part": "leftKnee",
        "position": {
            "x": 556.1034966140497,
            "y": 473.1014101337101
        }
    },
    {
        "score": 0.9222928881645203,
        "part": "rightKnee",
        "position": {
            "x": 477.0675474073066,
            "y": 487.43993118096193
        }
    },
    {
        "score": 0.3219120502471924,
        "part": "leftAnkle",
        "position": {
            "x": 543.9678709936924,
            "y": 493.32803463045497
        }
    },
    {
        "score": 0.1839255839586258,
        "part": "rightAnkle",
        "position": {
            "x": 469.31174606573387,
            "y": 484.90658736327873
        }
    }
]