[
    {
        "score": 0.9978232383728027,
        "part": "nose",
        "position": {
            "x": 339.8500874003426,
            "y": 149.20887808582103
        }
    },
    {
        "score": 0.9844818115234375,
        "part": "leftEye",
        "position": {
            "x": 345.70945964875773,
            "y": 139.62833465876918
        }
    },
    {
        "score": 0.998178243637085,
        "part": "rightEye",
        "position": {
            "x": 328.81567582927767,
            "y": 139.02393020534913
        }
    },
    {
        "score": 0.19831842184066772,
        "part": "leftEar",
        "position": {
            "x": 350.2458075851691,
            "y": 143.68761129893704
        }
    },
    {
        "score": 0.9708966612815857,
        "part": "rightEar",
        "position": {
            "x": 302.42451756899476,
            "y": 142.78198277801894
        }
    },
    {
        "score": 0.9578457474708557,
        "part": "leftShoulder",
        "position": {
            "x": 341.75379518602716,
            "y": 181.65393291172646
        }
    },
    {
        "score": 0.6994974613189697,
        "part": "rightShoulder",
        "position": {
            "x": 301.61903256275616,
            "y": 187.60606164259536
        }
    },
    {
        "score": 0.9164067506790161,
        "part": "leftElbow",
        "position": {
            "x": 372.35781410092216,
            "y": 216.96893506030327
        }
    },
    {
        "score": 0.43516361713409424,
        "part": "rightElbow",
        "position": {
            "x": 345.3718802029969,
            "y": 247.20748331536893
        }
    },
    {
        "score": 0.8923443555831909,
        "part": "leftWrist",
        "position": {
            "x": 443.32296352699154,
            "y": 202.91452684837753
        }
    },
    {
        "score": 0.820668637752533,
        "part": "rightWrist",
        "position": {
            "x": 410.78367239529973,
            "y": 284.24284270195545
        }
    },
    {
        "score": 0.9775328636169434,
        "part": "leftHip",
        "position": {
            "x": 320.3962622470543,
            "y": 312.1270609099835
        }
    },
    {
        "score": 0.966755747795105,
        "part": "rightHip",
        "position": {
            "x": 277.39567590932376,
            "y": 311.54520185161925
        }
    },
    {
        "score": 0.8988437652587891,
        "part": "leftKnee",
        "position": {
            "x": 353.40256387679307,
            "y": 374.12130387492203
        }
    },
    {
        "score": 0.7887235283851624,
        "part": "rightKnee",
        "position": {
            "x": 267.39642033811475,
            "y": 396.2844225628248
        }
    },
    {
        "score": 0.9120939373970032,
        "part": "leftAnkle",
        "position": {
            "x": 366.0160132236168,
            "y": 435.5598386392554
        }
    },
    {
        "score": 0.7852338552474976,
        "part": "rightAnkle",
        "position": {
            "x": 257.6061301309554,
            "y": 441.9872493664754
        }
    }
]