[
    {
        "score": 0.9995878338813782,
        "part": "nose",
        "position": {
            "x": 364.4113234222913,
            "y": 135.22796487412512
        }
    },
    {
        "score": 0.9985724687576294,
        "part": "leftEye",
        "position": {
            "x": 372.80502069191857,
            "y": 123.5938665777816
        }
    },
    {
        "score": 0.9967208504676819,
        "part": "rightEye",
        "position": {
            "x": 349.8270063556609,
            "y": 123.48549098889364
        }
    },
    {
        "score": 0.8105570077896118,
        "part": "leftEar",
        "position": {
            "x": 390.3983344406378,
            "y": 133.35363746184038
        }
    },
    {
        "score": 0.953087568283081,
        "part": "rightEar",
        "position": {
            "x": 331.2100569928279,
            "y": 131.6187349592502
        }
    },
    {
        "score": 0.9949865341186523,
        "part": "leftShoulder",
        "position": {
            "x": 418.62492495677515,
            "y": 200.6717752124264
        }
    },
    {
        "score": 0.9478716254234314,
        "part": "rightShoulder",
        "position": {
            "x": 297.807397060707,
            "y": 200.08641363921504
        }
    },
    {
        "score": 0.9001544713973999,
        "part": "leftElbow",
        "position": {
            "x": 494.57311711545856,
            "y": 212.0401532818173
        }
    },
    {
        "score": 0.6057838201522827,
        "part": "rightElbow",
        "position": {
            "x": 232.55259854676294,
            "y": 214.5717707907016
        }
    },
    {
        "score": 0.5985958576202393,
        "part": "leftWrist",
        "position": {
            "x": 579.0165455302255,
            "y": 222.42086853723805
        }
    },
    {
        "score": 0.9486106038093567,
        "part": "rightWrist",
        "position": {
            "x": 198.59537718725988,
            "y": 229.13193010195658
        }
    },
    {
        "score": 0.6111899018287659,
        "part": "leftHip",
        "position": {
            "x": 391.943859663166,
            "y": 387.54737426631186
        }
    },
    {
        "score": 0.9907082319259644,
        "part": "rightHip",
        "position": {
            "x": 330.53234513079536,
            "y": 382.6926437156329
        }
    },
    {
        "score": 0.17866365611553192,
        "part": "leftKnee",
        "position": {
            "x": 353.77478527631916,
            "y": 505.3159686045034
        }
    },
    {
        "score": 0.09925058484077454,
        "part": "rightKnee",
        "position": {
            "x": 326.62890424884733,
            "y": 493.2493797476361
        }
    },
    {
        "score": 0.12013833224773407,
        "part": "leftAnkle",
        "position": {
            "x": 329.13389512359123,
            "y": 492.7124655592986
        }
    },
    {
        "score": 0.06496657431125641,
        "part": "rightAnkle",
        "position": {
            "x": 336.54466472688273,
            "y": 489.81485426178614
        }
    }
]