[
    {
        "score": 0.999751627445221,
        "part": "nose",
        "position": {
            "x": 355.96691694415983,
            "y": 101.31962071810521
        }
    },
    {
        "score": 0.9993669390678406,
        "part": "leftEye",
        "position": {
            "x": 367.7894611045963,
            "y": 86.91093239052168
        }
    },
    {
        "score": 0.9992886185646057,
        "part": "rightEye",
        "position": {
            "x": 342.99959976946724,
            "y": 84.79513864794214
        }
    },
    {
        "score": 0.8693494200706482,
        "part": "leftEar",
        "position": {
            "x": 384.75413137967473,
            "y": 88.94533240448885
        }
    },
    {
        "score": 0.8748653531074524,
        "part": "rightEar",
        "position": {
            "x": 323.6672193183274,
            "y": 86.14911479079377
        }
    },
    {
        "score": 0.6247881054878235,
        "part": "leftShoulder",
        "position": {
            "x": 417.0554919633709,
            "y": 166.31641894331614
        }
    },
    {
        "score": 0.9904635548591614,
        "part": "rightShoulder",
        "position": {
            "x": 286.6781876360784,
            "y": 166.02334114278503
        }
    },
    {
        "score": 0.903447151184082,
        "part": "leftElbow",
        "position": {
            "x": 499.7476824150711,
            "y": 204.52500972510376
        }
    },
    {
        "score": 0.9709699153900146,
        "part": "rightElbow",
        "position": {
            "x": 206.1423504938845,
            "y": 189.94935221691844
        }
    },
    {
        "score": 0.7791905403137207,
        "part": "leftWrist",
        "position": {
            "x": 582.0597003874232,
            "y": 195.88107587885563
        }
    },
    {
        "score": 0.8196662068367004,
        "part": "rightWrist",
        "position": {
            "x": 96.11422579405738,
            "y": 199.5690532368743
        }
    },
    {
        "score": 0.959018886089325,
        "part": "leftHip",
        "position": {
            "x": 386.2043196881404,
            "y": 356.0944444411029
        }
    },
    {
        "score": 0.589614748954773,
        "part": "rightHip",
        "position": {
            "x": 311.5198434298156,
            "y": 353.55834545436244
        }
    },
    {
        "score": 0.8569434881210327,
        "part": "leftKnee",
        "position": {
            "x": 394.1698338242828,
            "y": 478.87045120302577
        }
    },
    {
        "score": 0.7919630408287048,
        "part": "rightKnee",
        "position": {
            "x": 305.9071917924725,
            "y": 473.176723693911
        }
    },
    {
        "score": 0.15768539905548096,
        "part": "leftAnkle",
        "position": {
            "x": 394.85432459096444,
            "y": 513.172191208329
        }
    },
    {
        "score": 0.5025637149810791,
        "part": "rightAnkle",
        "position": {
            "x": 310.76196989465933,
            "y": 494.0136611708962
        }
    }
]